[
	{
		"id":		"tvheadend_user",
		"label":	"Username",
		"type": 	"text",
		"default": 	"", 
	},
	{
		"id": 		"tvheadend_pass",
		"label": 	"Password",
		"type": 	"text",
		"option": 	"hidden",
		"default": 	"",
	},
	{
		"id": 		"tvheadend_host",
		"label": 	"Hostname or Ipaddress",
		"type": 	"text",
		"default": 	"", 
	},
	{
		"id":		"tvheadend_web_port",
		"label": 	"Web Port",
		"type": 	"text",
		"default": 	"9981", 
	},
        {
		"id":		"tvheadend_mpegts_passthrough",
		"label":	"MPEG-TS Pass-Through",
		"type":		"bool",
		"default":	"true",
        },
	{
		"id":		"tvheadend_custprof_default",
		"label":	"Custom default profile",
		"type":		"text",
		"default":	"",
	},
	{
		"id":           "tvheadend_custprof_ios",
		"label":        "Custom iOS profile",
		"type":         "text",
		"default":      "",
	},
	{
		"id":           "tvheadend_custprof_android",
		"label":        "Custom Android profile",
		"type":         "text",
		"default":      "",
	},
	{
		"id":		"tvheadend_channelicons",
		"label":	"Show channel icons",
		"type":		"bool",
		"default":	"true",
	},
	{
		"id":           "tvheadend_allchans",
		"label":        "Enable allchannels view",
		"type":         "bool",
		"default":      "true",
	},
	{
		"id":           "tvheadend_tagchans",
		"label":        "Enable bouquet view",
		"type":         "bool",
		"default":      "true",
	},
	{
		"id":           "tvheadend_recordings",
		"label":        "Enable Recordings view",
		"type":         "bool",
		"default":      "true",
	}
]
